Metadata-Version: 2.1
Name: distroverify
Version: 1.0.10
Summary: Utility to verify any linux distro file (*.iso) for its integrity
Home-page: https://github.com/prahladyeri/distroverify
Author: Prahlad Yeri
Author-email: prahladyeri@yahoo.com
License: MIT
Keywords: security,scanner
Platform: UNKNOWN
Classifier: Programming Language :: Python :: 3
Classifier: License :: OSI Approved :: MIT License
Classifier: Operating System :: OS Independent
Requires-Python: >= 3.4
